drb_impl_odata/__init__.py
drb_impl_odata/_version.py
drb_impl_odata/cache.py
drb_impl_odata/cortex.yml
drb_impl_odata/exceptions.py
drb_impl_odata/factory.py
drb_impl_odata/odata_node.py
drb_impl_odata/odata_nodes.py
drb_impl_odata/odata_services_nodes.py
drb_impl_odata/odata_utils.py
drb_impl_odata-1.0.7.data/data/requirements.txt
drb_impl_odata-1.0.7.dist-info/METADATA
drb_impl_odata-1.0.7.dist-info/WHEEL
drb_impl_odata-1.0.7.dist-info/entry_points.txt
drb_impl_odata-1.0.7.dist-info/top_level.txt
drb_impl_odata-1.0.7.dist-info/RECORD
