Metadata-Version: 2.1
Name: drb-impl-odata
Version: 1.0.7
Summary: DRB OData CSC implementation
Home-page: https://gitlab.com/drb-python/impl/odata
Author: GAEL Systems
Author-email: drb-python@gael.fr
License: UNKNOWN
Platform: UNKNOWN
Classifier: Programming Language :: Python :: 3.8
Classifier: License :: OSI Approved :: Apache Software License
Classifier: Operating System :: OS Independent
Requires-Python: >=3.8
Requires-Dist: drb (<1.1.0,>=1.0.4)
Requires-Dist: drb-impl-http (<1.1.0,>=1.0.7)
Requires-Dist: defusedxml (>=0.7.1)
Requires-Dist: drb-impl-json (<1.1.0,>=1.0.1)
